cerridwen/__init__.py
cerridwen/api_server.py
cerridwen/approximate.py
cerridwen/cli.py
cerridwen/defs.py
cerridwen/event_generator.py
cerridwen/planets.py
cerridwen/sandbox.py
cerridwen/tests.py
cerridwen/utils.py
cerridwen/version.py
cerridwen-1.4.1.dist-info/DESCRIPTION.rst
cerridwen-1.4.1.dist-info/METADATA
cerridwen-1.4.1.dist-info/RECORD
cerridwen-1.4.1.dist-info/WHEEL
cerridwen-1.4.1.dist-info/entry_points.txt
cerridwen-1.4.1.dist-info/metadata.json
cerridwen-1.4.1.dist-info/top_level.txt
