Metadata-Version: 2.0
Name: cerridwen
Version: 1.4.1
Summary: Accurate solar system data for everyone
Home-page: http://cerridwen.bluemagician.vc/
Author: Leslie P. Polzer
Author-email: polzer@fastmail.com
License: MIT
Platform: UNKNOWN
Classifier: Development Status :: 4 - Beta
Classifier: Environment :: Console
Classifier: Intended Audience :: Science/Research
Classifier: Intended Audience :: Developers
Classifier: License :: OSI Approved :: MIT License
Classifier: Operating System :: OS Independent
Classifier: Programming Language :: Python :: 3
Classifier: Topic :: Scientific/Engineering :: Astronomy
Classifier: Topic :: Other/Nonlisted Topic
Classifier: Topic :: Software Development :: Libraries :: Python Modules
Classifier: Topic :: Utilities
Requires: pyswisseph
Requires: numpy
Requires: astropy(>=0.4)
Provides-Extra: Flask
Requires-Dist: flask; extra == 'Flask'
